{
  "resolvedId": "/home/justin/Documents/chat-web-client/src/routes/index.tsx",
  "transforms": [
    {
      "name": "__load__",
      "result": "import { Title } from \"solid-start\";\nimport ChatWindow from \"~/components/ChatWindow\";\nimport Counter from \"~/components/Counter\";\n\nexport default function Home() {\n  return (\n    <main>\n        <ChatWindow/>\n    </main>\n  );\n}\n",
      "start": 1683869513811,
      "end": 1683869513811
    },
    {
      "name": "solid-start-file-system-router",
      "result": "import { template as _$template } from \"solid-js/web\";\nimport { getNextElement as _$getNextElement } from \"solid-js/web\";\nimport { insert as _$insert } from \"solid-js/web\";\nimport { createComponent as _$createComponent } from \"solid-js/web\";\nconst _tmpl$ = /*#__PURE__*/_$template(`<main>`);\nimport ChatWindow from \"~/components/ChatWindow\";\nexport default function Home() {\n  return (() => {\n    const _el$ = _$getNextElement(_tmpl$);\n    _$insert(_el$, _$createComponent(ChatWindow, {}));\n    return _el$;\n  })();\n}",
      "start": 1683869513811,
      "end": 1683869513816,
      "order": "pre"
    },
    {
      "name": "solid",
      "result": "import { $$component as _$$component } from \"solid-refresh\";\nimport { $$refresh as _$$refresh } from \"solid-refresh\";\nimport { $$registry as _$$registry } from \"solid-refresh\";\nconst _REGISTRY = _$$registry();\nimport { template as _$template } from \"solid-js/web\";\nimport { getNextElement as _$getNextElement } from \"solid-js/web\";\nimport { insert as _$insert } from \"solid-js/web\";\nimport { createComponent as _$createComponent } from \"solid-js/web\";\nconst _tmpl$ = /*#__PURE__*/_$template(`<main>`);\nimport ChatWindow from \"~/components/ChatWindow\";\nexport default _$$component(_REGISTRY, \"Home\", function Home() {\n  return (() => {\n    const _el$ = _$getNextElement(_tmpl$);\n    _$insert(_el$, _$createComponent(ChatWindow, {}));\n    return _el$;\n  })();\n}, {\n  location: \"src/routes/index.tsx:7:15\"\n});\nif (import.meta.hot) {\n  _$$refresh(\"vite\", import.meta.hot, _REGISTRY);\n  import.meta.hot.accept();\n}",
      "start": 1683869513816,
      "end": 1683869513824,
      "order": "pre"
    },
    {
      "name": "vite:import-analysis",
      "result": "import { createHotContext as __vite__createHotContext } from \"/@vite/client\";import.meta.hot = __vite__createHotContext(\"/src/routes/index.tsx\");import { $$component as _$$component } from \"/@solid-refresh\";\nimport { $$refresh as _$$refresh } from \"/@solid-refresh\";\nimport { $$registry as _$$registry } from \"/@solid-refresh\";\nconst _REGISTRY = _$$registry();\nimport { template as _$template } from \"/node_modules/.vite/deps/solid-js_web.js?v=1564f02c\";\nimport { getNextElement as _$getNextElement } from \"/node_modules/.vite/deps/solid-js_web.js?v=1564f02c\";\nimport { insert as _$insert } from \"/node_modules/.vite/deps/solid-js_web.js?v=1564f02c\";\nimport { createComponent as _$createComponent } from \"/node_modules/.vite/deps/solid-js_web.js?v=1564f02c\";\nconst _tmpl$ = /*#__PURE__*/_$template(`<main>`);\nimport ChatWindow from \"/src/components/ChatWindow.tsx\";\nexport default _$$component(_REGISTRY, \"Home\", function Home() {\n  return (() => {\n    const _el$ = _$getNextElement(_tmpl$);\n    _$insert(_el$, _$createComponent(ChatWindow, {}));\n    return _el$;\n  })();\n}, {\n  location: \"src/routes/index.tsx:7:15\"\n});\nif (import.meta.hot) {\n  _$$refresh(\"vite\", import.meta.hot, _REGISTRY);\n  import.meta.hot.accept();\n}",
      "start": 1683869513824,
      "end": 1683869513825,
      "order": "normal"
    }
  ]
}
